telemetry_manager/__init__.py
telemetry_manager/manager.py
telemetry_manager/common/__init__.py
telemetry_manager/common/manager.py
telemetry_manager/common/resource.py
telemetry_manager/common/settings_file.py
telemetry_manager/log/__init__.py
telemetry_manager/log/manager.py
telemetry_manager/metric/__init__.py
telemetry_manager/metric/manager.py
telemetry_manager/trace/__init__.py
telemetry_manager/trace/manager.py
telemetry_manager-1.1.5.dist-info/LICENSE
telemetry_manager-1.1.5.dist-info/METADATA
telemetry_manager-1.1.5.dist-info/WHEEL
telemetry_manager-1.1.5.dist-info/top_level.txt
telemetry_manager-1.1.5.dist-info/RECORD
